{
  "unversionedId": "Areas of Focus/Scrum Artifacts",
  "id": "Areas of Focus/Scrum Artifacts",
  "title": "Scrum Artifacts",
  "description": "This is the easy tutorial!",
  "source": "@site/docs/2. Areas of Focus/Scrum Artifacts.md",
  "sourceDirName": "2. Areas of Focus",
  "slug": "/Areas of Focus/Scrum Artifacts",
  "permalink": "/docs/Areas of Focus/Scrum Artifacts",
  "draft": false,
  "tags": [
    {
      "label": "Scrum",
      "permalink": "/docs/tags/scrum"
    },
    {
      "label": "AOF",
      "permalink": "/docs/tags/aof"
    }
  ],
  "version": "current",
  "sidebarPosition": 3,
  "frontMatter": {
    "title": "Scrum Artifacts",
    "sidebar_position": 3,
    "tags": [
      "Scrum",
      "AOF"
    ]
  },
  "sidebar": "tutorialSidebar",
  "previous": {
    "title": "Scrum Roles",
    "permalink": "/docs/Areas of Focus/Scrum Roles"
  },
  "next": {
    "title": "Scrum Events",
    "permalink": "/docs/Areas of Focus/Scrum Events"
  }
}